fulladder.sv
module full_adder (
    input wire a,     // First input
    input wire b,     // Second input
    input wire cin,   // Carry input
    output wire sum,  // Sum output
    output wire cout  // Carry output
);
    assign {cout, sum} = a + b + cin; // Full adder logic
endmodule

fulladderTB.sv
`include "fulladder.sv"
module tb_full_adder;
    // Inputs
    reg a;
    reg b;
    reg cin;

    // Outputs
    wire sum;
    wire cout;
    
    // Instantiate the full adder
    full_adder uut (
        .a(a),
        .b(b),
        .cin(cin),
        .sum(sum),
        .cout(cout)
    );
    
    // Test cases
    initial begin
        // Test case 1: 0 + 0 + 0 = 0, carry = 0
        a = 0; b = 0; cin = 0;
        #10; // Wait for 10 time units
        $display("Test case 1: a = %b, b = %b, cin = %b -> sum = %b, cout = %b", a, b, cin, sum, cout);
        
        // Test case 2: 0 + 0 + 1 = 1, carry = 0
        a = 0; b = 0; cin = 1;
        #10; // Wait for 10 time units
        $display("Test case 2: a = %b, b = %b, cin = %b -> sum = %b, cout = %b", a, b, cin, sum, cout);
        
        // Test case 3: 0 + 1 + 0 = 1, carry = 0
        a = 0; b = 1; cin = 0;
        #10; // Wait for 10 time units
        $display("Test case 3: a = %b, b = %b, cin = %b -> sum = %b, cout = %b", a, b, cin, sum, cout);
        
        // Test case 4: 0 + 1 + 1 = 0, carry = 1
        a = 0; b = 1; cin = 1;
        #10; // Wait for 10 time units
        $display("Test case 4: a = %b, b = %b, cin = %b -> sum = %b, cout = %b", a, b, cin, sum, cout);
        
        // Test case 5: 1 + 0 + 0 = 1, carry = 0
        a = 1; b = 0; cin = 0;
        #10; // Wait for 10 time units
        $display("Test case 5: a = %b, b = %b, cin = %b -> sum = %b, cout = %b", a, b, cin, sum, cout);
        
        // Test case 6: 1 + 0 + 1 = 0, carry = 1
        a = 1; b = 0; cin = 1;
        #10; // Wait for 10 time units
        $display("Test case 6: a = %b, b = %b, cin = %b -> sum = %b, cout = %b", a, b, cin, sum, cout);
        
        // Test case 7: 1 + 1 + 0 = 0, carry = 1
        a = 1; b = 1; cin = 0;
        #10; // Wait for 10 time units
        $display("Test case 7: a = %b, b = %b, cin = %b -> sum = %b, cout = %b", a, b, cin, sum, cout);
        
        // Test case 8: 1 + 1 + 1 = 1, carry = 1
        a = 1; b = 1; cin = 1;
        #10; // Wait for 10 time units
        $display("Test case 8: a = %b, b = %b, cin = %b -> sum = %b, cout = %b", a, b, cin, sum, cout);
        
        $finish; // End the simulation
    end

    initial begin
    $dumpfile("fulladder.vcd");
    $dumpvars;
    end
endmodule

fulladder.vcd
$date
	Mon Jun 24 14:45:50 2024
$end

$version
	Synopsys VCS version T-2022.06-SP2_Full64
$end

$timescale
	1s
$end

$comment Csum: 1 4df47c7750d31b64 $end


$scope module tb_full_adder $end
$var reg 1 ! a $end
$var reg 1 " b $end
$var reg 1 # cin $end
$var wire 1 $ sum $end
$var wire 1 % cout $end

$scope module uut $end
$var wire 1 ! a $end
$var wire 1 " b $end
$var wire 1 # cin $end
$var wire 1 $ sum $end
$var wire 1 % cout $end
$upscope $end

$upscope $end

$enddefinitions $end

#0
$dumpvars
0!
0"
0#
x$
x%
$end
0$
0%
#10
1#
1$
#20
1"
0#
#30
1#
0$
1%
#40
1!
0"
0#
1$
0%
#50
1#
0$
1%
#60
1"
0#
#70
1#
1$
